__init__.py
notation_calc.py
smart_notation-0.0.1.dist-info/licenses/LICENCE
smart_notation-0.0.1.dist-info/METADATA
smart_notation-0.0.1.dist-info/WHEEL
smart_notation-0.0.1.dist-info/top_level.txt
smart_notation-0.0.1.dist-info/RECORD
